LICENSE
MANIFEST.in
README.md
setup.cfg
setup.py
pxprocess/__init__.py
pxprocess/api.py
pxprocess.egg-info/PKG-INFO
pxprocess.egg-info/SOURCES.txt
pxprocess.egg-info/dependency_links.txt
pxprocess.egg-info/top_level.txt