Metadata-Version: 1.1
Name: pxprocess
Version: 0.0.3
Summary: Friendly replacement for subprocess
Home-page: http://github.com/Pixelapse/pxprocess
Author: Pixelapse
Author-email: hello@pixelapse.com
License: The MIT License (MIT)
